{"wordIndexes":{"هل":[1],"أتيك":[2],"حديث":[3],"الغشية":[4],"وجوه":[5,29],"يومئذ":[6,30],"خشعة":[7],"عاملة":[8],"ناصبة":[9],"تصلى":[10],"نارا":[11],"حامية":[12],"تسقى":[13],"من":[14,21,27,79],"عين":[15,42],"آنية":[16],"ليس":[17],"لهم":[18],"طعام":[19],"إلا":[20,78],"ضريع":[22],"لا":[23,37],"يسمن":[24],"ولا":[25],"يغني":[26],"جوع":[28],"ناعمة":[31],"لسعيها":[32],"راضية":[33],"في":[34],"جنة":[35],"عالية":[36],"تسمع":[38],"فيها":[39,41,44],"لغية":[40],"جارية":[43],"سرر":[45],"مرفوعة":[46],"وأكواب":[47],"موضوعة":[48],"ونمارق":[49],"مصفوفة":[50],"وزرابي":[51],"مبثوثة":[52],"أفلا":[53],"ينظرون":[54],"إلى":[55],"الإبل":[56],"كيف":[57,61,65,69],"خلقت":[58],"وإلى":[59,63,67],"السماء":[60],"رفعت":[62],"الجبال":[64],"نصبت":[66],"الأرض":[68],"سطحت":[70],"فذكر":[71],"إنما":[72],"أنت":[73],"مذكر":[74],"لست":[75],"عليهم":[76],"بمصيطر":[77],"تولى":[80],"وكفر":[81],"فيعذبه":[82],"الله":[83],"العذاب":[84],"الأكبر":[85],"إن":[86,90],"إلينا":[87],"إيابهم":[88],"ثم":[89],"علينا":[91],"حسابهم":[92]}}